xpuls_fastapi_utils/__init__.py
xpuls_fastapi_utils/constants/__init__.py
xpuls_fastapi_utils/core/__init__.py
xpuls_fastapi_utils/core/common.py
xpuls_fastapi_utils/logging/__init__.py
xpuls_fastapi_utils/logging/fastapi_log_config.py
xpuls_fastapi_utils/logging/setup_logger.py
xpuls_fastapi_utils/server/__init__.py
xpuls_fastapi_utils/server/common.py
xpuls_fastapi_utils/server/route_handlers/__init__.py
xpuls_fastapi_utils/server/route_handlers/telemetry.py
xpuls_fastapi_utils/telemetry/__init__.py
xpuls_fastapi_utils/utils/__init__.py
xpuls_fastapi_utils-0.0.2.dist-info/LICENSE
xpuls_fastapi_utils-0.0.2.dist-info/METADATA
xpuls_fastapi_utils-0.0.2.dist-info/WHEEL
xpuls_fastapi_utils-0.0.2.dist-info/top_level.txt
xpuls_fastapi_utils-0.0.2.dist-info/RECORD
