Metadata-Version: 2.1
Name: xpuls-fastapi-utils
Version: 0.0.2
Summary: Base SDK for FastAPI Utils
Home-page: https://github.com/xpuls-labs/fastapi-utils
Author: Sai Sharan Tangeda
Author-email: saisarantangeda@gmail.com
License-File: LICENSE
Requires-Dist: setuptools
Requires-Dist: wheel
Requires-Dist: pydantic
Requires-Dist: pyyaml
Requires-Dist: fastapi
Requires-Dist: uvicorn[standard]
Requires-Dist: starlette-exporter
Requires-Dist: starlette
Requires-Dist: pytest
